{"region_data":{"countryId":"2245662","adminCode1":"01","countryName":"Senegal","fclName":"country, state, region,...","countryCode":"SN","lng":"-17.28333","fcodeName":"first-order administrative division","toponymName":"Dakar","fcl":"A","numberOfChildren":4,"name":"Dakar","fcode":"ADM1","geonameId":2253350,"lat":"14.76667","adminName1":"Dakar","population":2431062},"country_data":{"ISO":"SN","ISO3":"SEN","ISO_Numeric":"686","fips":"SG","country":"Senegal","capital":"Dakar","area":"196190","Population":"12323252","Continent":"AF","tld":".sn","CurrencyCode":"XOF","CurrencyName":"Franc","Phone":"221","Postal_Code_Format":"#####","Postal_Code_Regex":"^(\\d{5})$","Languages":"fr-SN,wo,fuc,mnk","geonameid":"2245662","neighbours":"GN,MR,GW,GM,ML","EquivalentFipsCode":""},"cities":[]}